Flask_Z3950-1.0.1.dist-info/DESCRIPTION.rst
Flask_Z3950-1.0.1.dist-info/METADATA
Flask_Z3950-1.0.1.dist-info/RECORD
Flask_Z3950-1.0.1.dist-info/WHEEL
Flask_Z3950-1.0.1.dist-info/metadata.json
Flask_Z3950-1.0.1.dist-info/top_level.txt
flask_z3950/__init__.py
flask_z3950/blueprint.py
flask_z3950/dataset.py
flask_z3950/view.py
flask_z3950/z3950.py
flask_z3950/templates/error.xml
flask_z3950/templates/success.html
flask_z3950/xsl/format-xml.xsl
flask_z3950/xsl/marcxml-to-html.xsl
