Metadata-Version: 2.0
Name: Flask-Z3950
Version: 1.0.1
Summary: Z39.50 integration for Flask applications.
Home-page: https://github.com/alexandermendes/Flask-Z3950
Author: Alexander Mendes
Author-email: alexanderhmendes@gmail.com
License: BSD
Platform: any
Classifier: Development Status :: 5 - Production/Stable
Classifier: Environment :: Web Environment
Classifier: Intended Audience :: Developers
Classifier: License :: OSI Approved :: BSD License
Classifier: Operating System :: OS Independent
Classifier: Programming Language :: Python :: 2.6
Classifier: Programming Language :: Python :: 2.7
Classifier: Topic :: Internet :: WWW/HTTP :: Dynamic Content
Classifier: Topic :: Software Development :: Libraries :: Python Modules
Classifier: Topic :: Internet :: Z39.50
Requires-Dist: Flask (>=0.7.0)
Requires-Dist: lxml (>=3.5.0,<4.0)
Requires-Dist: mollyZ3950 (==2.04-molly1)
Requires-Dist: ply (>=3.8.0,<4.0)
Requires-Dist: pymarc (>=3.0.4,<4.0)
